madaline_johns_sdk-2.2.2.dist-info/licenses/LICENSE
paypalrestapis/__init__.py
paypalrestapis/api_helper.py
paypalrestapis/configuration.py
paypalrestapis/paypalrestapis_client.py
paypalrestapis/controllers/__init__.py
paypalrestapis/controllers/base_controller.py
paypalrestapis/controllers/o_auth_authorization_controller.py
paypalrestapis/controllers/orders_controller.py
paypalrestapis/controllers/payments_controller.py
paypalrestapis/controllers/vault_controller.py
paypalrestapis/exceptions/__init__.py
paypalrestapis/exceptions/api_exception.py
paypalrestapis/exceptions/error_exception.py
paypalrestapis/exceptions/o_auth_provider_exception.py
paypalrestapis/http/__init__.py
paypalrestapis/http/http_call_back.py
paypalrestapis/http/http_method_enum.py
paypalrestapis/http/http_request.py
paypalrestapis/http/http_response.py
paypalrestapis/http/auth/__init__.py
paypalrestapis/http/auth/o_auth_2.py
paypalrestapis/logging/__init__.py
paypalrestapis/logging/sdk_logger.py
paypalrestapis/logging/configuration/__init__.py
paypalrestapis/logging/configuration/api_logging_configuration.py
paypalrestapis/models/__init__.py
paypalrestapis/models/ach_debit_response.py
paypalrestapis/models/activity_timestamps.py
paypalrestapis/models/address.py
paypalrestapis/models/address_details.py
paypalrestapis/models/amount_breakdown.py
paypalrestapis/models/amount_with_breakdown.py
paypalrestapis/models/apple_pay_attributes.py
paypalrestapis/models/apple_pay_attributes_response.py
paypalrestapis/models/apple_pay_card.py
paypalrestapis/models/apple_pay_card_response.py
paypalrestapis/models/apple_pay_decrypted_token_data.py
paypalrestapis/models/apple_pay_payment_data.py
paypalrestapis/models/apple_pay_payment_data_type.py
paypalrestapis/models/apple_pay_payment_object.py
paypalrestapis/models/apple_pay_payment_token.py
paypalrestapis/models/apple_pay_request.py
paypalrestapis/models/apple_pay_tokenized_card.py
paypalrestapis/models/authentication_response.py
paypalrestapis/models/authorization.py
madaline_johns_sdk-2.2.2.dist-info/METADATA
madaline_johns_sdk-2.2.2.dist-info/WHEEL
madaline_johns_sdk-2.2.2.dist-info/top_level.txt
madaline_johns_sdk-2.2.2.dist-info/RECORD
