Metadata-Version: 2.4
Name: madaline-johns-sdk
Version: 2.2.2
Summary: Voluptate qui ex qui
Author-email: Sebastian Petty <vocop@mailinator.com>
Requires-Python: >=3.7
License-File: LICENSE
Requires-Dist: apimatic-core>=0.2.17,~=0.2.0
Requires-Dist: apimatic-core-interfaces>=0.1.5,~=0.1.0
Requires-Dist: apimatic-requests-client-adapter>=0.1.6,~=0.1.0
Provides-Extra: testutils
Requires-Dist: pytest>=7.2.2; extra == "testutils"
Dynamic: license-file
